khivemcp/__init__.py
khivemcp/cli.py
khivemcp/decorators.py
khivemcp/function_call_parser.py
khivemcp/groups.py
khivemcp/logging_config.py
khivemcp/py.typed
khivemcp/runner.py
khivemcp/server.py
khivemcp/tool_spec.py
khivemcp/tools.py
khivemcp/types.py
khivemcp/utils.py
khivemcp-1.2.0.dist-info/METADATA
khivemcp-1.2.0.dist-info/WHEEL
khivemcp-1.2.0.dist-info/entry_points.txt
khivemcp-1.2.0.dist-info/licenses/LICENSE
khivemcp-1.2.0.dist-info/RECORD
