Metadata-Version: 2.4
Name: khivemcp
Version: 1.2.0
Summary: An easy mcp deployment framework
Author-email: HaiyangLi <quantocean.li@gmail.com>
License:            Apache License
License-File: LICENSE
Classifier: Framework :: Pydantic
Classifier: Framework :: Pydantic :: 2
Classifier: Framework :: Pytest
Classifier: Intended Audience :: Developers
Classifier: License :: OSI Approved :: Apache Software License
Classifier: Operating System :: OS Independent
Classifier: Programming Language :: Python :: 3
Classifier: Programming Language :: Python :: 3 :: Only
Classifier: Programming Language :: Python :: 3.10
Classifier: Programming Language :: Python :: 3.11
Classifier: Programming Language :: Python :: 3.12
Classifier: Programming Language :: Python :: 3.13
Requires-Python: >=3.10
Requires-Dist: fastmcp>=2.12.0
Requires-Dist: pydantic>=2.0.0
Requires-Dist: pyyaml>=5.3.1
Requires-Dist: typer>=0.15.0
Requires-Dist: uvicorn>=0.30.0
Provides-Extra: examples
Requires-Dist: lionagi>=0.18.1; extra == 'examples'
